exec_across_windows/__init__.py
exec_across_windows/exec_across_windows.py
exec_across_windows-1.0.4.dist-info/licenses/LICENSE
exec_across_windows-1.0.4.dist-info/METADATA
exec_across_windows-1.0.4.dist-info/WHEEL
exec_across_windows-1.0.4.dist-info/entry_points.txt
exec_across_windows-1.0.4.dist-info/top_level.txt
exec_across_windows-1.0.4.dist-info/RECORD
