Metadata-Version: 2.4
Name: exec-across-windows
Version: 1.0.4
Summary: Execute commands across Windows systems using multiple RCE methods (WinRM, SMB, WMI, RDP, SSH, MSSQL)
Author: Khael
Project-URL: Homepage, https://github.com/KhaelK138/exec-across-windows
Project-URL: Repository, https://github.com/KhaelK138/exec-across-windows
Project-URL: Issues, https://github.com/KhaelK138/exec-across-windows/issues
Keywords: security,pentest,windows,remote-execution,winrm,smb,wmi,rdp
Classifier: Development Status :: 4 - Beta
Classifier: Intended Audience :: Information Technology
Classifier: Intended Audience :: System Administrators
Classifier: Programming Language :: Python :: 3
Classifier: Programming Language :: Python :: 3.8
Classifier: Programming Language :: Python :: 3.9
Classifier: Programming Language :: Python :: 3.10
Classifier: Programming Language :: Python :: 3.11
Classifier: Programming Language :: Python :: 3.12
Classifier: Topic :: Security
Classifier: Topic :: System :: Systems Administration
Requires-Python: >=3.8
License-File: LICENSE
Provides-Extra: dev
Requires-Dist: build; extra == "dev"
Requires-Dist: twine; extra == "dev"
Dynamic: license-file
